{
  "categories": [
    {
      "key": "business",
      "name": "商业Business",
      "icon": "💼"
    },
    {
      "key": "data",
      "name": "数据Data",
      "icon": "📊"
    },
    {
      "key": "design",
      "name": "设计Design",
      "icon": "🎨"
    },
    {
      "key": "education",
      "name": "教育Education",
      "icon": "📚"
    },
    {
      "key": "life",
      "name": "生活Life",
      "icon": "🏠"
    },
    {
      "key": "professional",
      "name": "职业Professional",
      "icon": "💼"
    },
    {
      "key": "writing",
      "name": "写作Writing",
      "icon": "✍️"
    }
  ],
  "skills": [
    {
      "id": "biz-plan",
      "name": "Biz Plan",
      "category": "商业Business",
      "categoryKey": "business",
      "icon": "📄",
      "description": "商业计划书编写技能。帮助撰写创业/融资用的商业计划书，包含市场分析、商业模式、财务预测等完整框架。",
      "whenToUse": "商业计划书、融资计划、创业规划、项目可行性",
      "systemPrompt": "帮助撰写专业的商业计划书，包含执行摘要、市场分析、商业模式、竞争分析、财务预测等完整内容。",
      "inputFormat": "**基础信息（必需）**：\n```\n项目/公司名称：\n所属行业：\n融资阶段（如适用）：\n目标融资额：\n项目简介（100字以内）：\n```\n\n**可选补充信息**：\n- 已有业务数据（用户数、收入、增长率等）\n- 团队背景简介\n- 竞品信息\n- 商业模式描述",
      "path": "business\\biz-plan"
    },
    {
      "id": "competitor-analysis",
      "name": "Competitor Analysis",
      "category": "商业Business",
      "categoryKey": "business",
      "icon": "📄",
      "description": "竞品分析研究技能。帮助分析竞争对手的产品、市场定位、功能策略、价格策略等，提供洞察和决策支持。",
      "whenToUse": "竞品分析、市场研究、竞争策略、产品规划",
      "systemPrompt": "系统性地分析竞争对手，了解市场竞争格局，为产品决策提供支持。",
      "inputFormat": "**必需信息**：\n```\n分析目的：[产品规划/融资/定价/战略...]\n目标市场/产品类别：[具体描述]\n分析深度：[快速概览/深度分析/全面调研]\n```\n\n**可选补充**：\n- 已有竞品列表\n- 特定竞品需重点分析\n- 时间/资源约束\n- 已有竞品信息（如体验报告）",
      "path": "business\\competitor-analysis"
    },
    {
      "id": "contract-review",
      "name": "Contract Review",
      "category": "商业Business",
      "categoryKey": "business",
      "icon": "📄",
      "description": "合同风险审查技能。帮助审查合同条款，识别潜在风险点，提供修改建议，保护企业利益。",
      "whenToUse": "合同审查、法律风险、商业合同、合作协议",
      "systemPrompt": "帮助审查合同条款，识别法律风险和商业风险，提供修改建议。",
      "inputFormat": "**必需信息**：\n```\n合同名称：[合同标题]\n合同类型：[技术服务/采购/销售/租赁/其他]\n合同金额：[金额，如有]\n签约背景：[简要说明签约目的]\n```\n\n**可选补充**：\n- 合同文本（全文或关键条款）\n- 对方公司背景\n- 已有谈判记录\n- 特殊需求或顾虑",
      "path": "business\\contract-review"
    },
    {
      "id": "decision-matrix",
      "name": "Decision Matrix",
      "category": "商业Business",
      "categoryKey": "business",
      "icon": "📄",
      "description": "决策分析工具技能。帮助使用加权评分法、利弊分析、情景分析等方法进行系统性决策。",
      "whenToUse": "决策分析、方案对比、利弊分析、加权评分",
      "systemPrompt": "帮助进行系统性决策分析，使用多种分析框架支持决策。",
      "inputFormat": "**必需信息**：\n```\n决策问题：[描述要解决的问题]\n可选方案：[列出所有选项]\n决策目的：[优化什么]\n```\n\n**可选补充**：\n- 已有方案信息\n- 决策约束（预算、时间等）\n- 利益相关者\n- 风险偏好",
      "path": "business\\decision-matrix"
    },
    {
      "id": "financial-analysis",
      "name": "Financial Analysis",
      "category": "商业Business",
      "categoryKey": "business",
      "icon": "📄",
      "description": "财务报表分析技能。帮助分析财务报表（资产负债表、利润表、现金流量表），提供财务健康度评估。",
      "whenToUse": "财务分析、报表解读、投资评估、经营诊断",
      "systemPrompt": "帮助分析财务报表，评估企业财务健康状况，识别潜在风险和机会。",
      "inputFormat": "**必需信息**：\n```\n分析对象：[公司名称]\n分析周期：[年度/季度/年报/季报]\n财务数据：[三张表或关键指标]\n分析目的：[投资/诊断/对标/融资]\n```\n\n**可选补充**：\n- 行业背景\n- 竞品财务数据\n- 历史财务数据\n- 非财务信息（业务动态、管理层）",
      "path": "business\\financial-analysis"
    },
    {
      "id": "growth-hacking",
      "name": "Growth Hacking",
      "category": "商业Business",
      "categoryKey": "business",
      "icon": "📄",
      "description": "用户增长策略技能。帮助制定用户增长策略，包括裂变活动、留存优化、召回机制等，提升用户量。",
      "whenToUse": "用户增长、裂变活动、留存提升、增长黑客",
      "systemPrompt": "帮助制定用户增长策略，利用增长黑客思维，通过裂变、留存优化、召回等手段提升用户量。",
      "inputFormat": "**必需信息**：\n```\n产品类型：[C端/B端/平台型]\n当前阶段：[用户量/日活/月活]\n增长目标：[目标用户量/增长率]\n核心指标：[DAU/MAU/新增等]\n```\n\n**可选补充**：\n- 当前增长瓶颈\n- 已有增长数据\n- 竞品增长策略\n- 预算限制",
      "path": "business\\growth-hacking"
    },
    {
      "id": "investment-eval",
      "name": "Investment Eval",
      "category": "商业Business",
      "categoryKey": "business",
      "icon": "📄",
      "description": "项目估值与投资分析技能。帮助评估项目/公司价值，包括DCF估值、可比公司法、早期估值等。",
      "whenToUse": "投资分析、项目估值、尽职调查、融资定价",
      "systemPrompt": "帮助评估投资标的的价值，包括早期项目和成熟企业。",
      "inputFormat": "**必需信息**：\n```\n标的名称：[公司/项目名称]\n发展阶段：[种子轮/天使轮/A轮/B轮/成长期/成熟期]\n行业：[行业分类]\n评估目的：[投资/融资/内部评估]\n```\n\n**可选补充**：\n- 财务数据（营收、利润、现金流）\n- 运营数据（用户数、GMV、ARR）\n- 历史融资情况\n- 团队背景\n- 竞品估值信息",
      "path": "business\\investment-eval"
    },
    {
      "id": "marketing-plan",
      "name": "Marketing Plan",
      "category": "商业Business",
      "categoryKey": "business",
      "icon": "📄",
      "description": "营销方案制定技能。帮助制定全面的营销方案，包括渠道策略、内容策略、预算分配和ROI预估。",
      "whenToUse": "营销策划、市场推广、增长策略、预算规划",
      "systemPrompt": "帮助制定完整的营销方案，覆盖渠道选择、内容策略、预算分配和效果追踪。",
      "inputFormat": "**必需信息**：\n```\n产品/服务：[名称]\n营销目标：[具体目标]\n目标用户：[用户画像]\n营销预算：[金额]\n营销周期：[时间范围]\n```\n\n**可选补充**：\n- 产品卖点\n- 竞品营销动作\n- 已有营销资源\n- 销售渠道",
      "path": "business\\marketing-plan"
    },
    {
      "id": "meeting-notes",
      "name": "Meeting Notes",
      "category": "商业Business",
      "categoryKey": "business",
      "icon": "📄",
      "description": "会议纪要生成技能。帮助从会议内容中提取关键信息，生成结构化的会议纪要，包含决策、行动项和跟进。",
      "whenToUse": "会议记录、周会纪要、会议总结、行动项跟踪",
      "systemPrompt": "帮助整理会议内容，生成清晰的会议纪要，包括讨论要点、决策结论、行动项和责任人。",
      "inputFormat": "**必需信息**：\n```\n会议主题：[主题名称]\n会议时间：[日期时间]\n参会人员：[人员列表]\n会议目的：[简要说明]\n```\n\n**可选补充**：\n- 会议议程\n- 会议录音/视频\n- 会议前的相关文档\n- 之前的会议纪要（延续性会议）",
      "path": "business\\meeting-notes"
    },
    {
      "id": "okr-helper",
      "name": "Okr Helper",
      "category": "商业Business",
      "categoryKey": "business",
      "icon": "📄",
      "description": "OKR制定与追踪技能。帮助制定OKR（目标与关键结果），追踪进度并协助复盘。",
      "whenToUse": "OKR制定、目标管理、绩效追踪、团队管理",
      "systemPrompt": "帮助制定OKR（Objectives and Key Results），追踪进度并协助复盘。",
      "inputFormat": "**必需信息**：\n```\n组织层级：[公司/部门/团队/个人]\n目标周期：[Q1/Q2/Q3/Q4/半年/年]\n制定者：[姓名/角色]\n```\n\n**可选补充**：\n- 上周期OKR（延续性目标）\n- 业务背景和优先级\n- 团队规模和能力\n- 已有数据指标",
      "path": "business\\okr-helper"
    },
    {
      "id": "prd-writer",
      "name": "Prd Writer",
      "category": "商业Business",
      "categoryKey": "business",
      "icon": "📄",
      "description": "需求文档编写技能。帮助撰写专业的PRD（产品需求文档），包含功能需求、非功能需求、验收标准等。",
      "whenToUse": "PRD撰写、需求文档、产品规划、功能定义",
      "systemPrompt": "帮助撰写专业的PRD产品需求文档，确保需求清晰、完整、可执行。",
      "inputFormat": "**必需信息**：\n```\n产品名称：[名称]\n功能名称：[名称，如是新功能则必填]\n文档版本：[如V1.0]\n产品经理：[姓名]\n```\n\n**可选补充**：\n- 产品背景和目标\n- 需求来源（用户反馈/数据/业务）\n- 期望上线时间\n- 相关需求文档（已有功能/系统）\n- 技术约束说明",
      "path": "business\\prd-writer"
    },
    {
      "id": "pricing-strategy",
      "name": "Pricing Strategy",
      "category": "商业Business",
      "categoryKey": "business",
      "icon": "📄",
      "description": "定价策略分析技能。帮助分析定价策略，包括成本加成、竞争定价、价值定价等，优化收入结构。",
      "whenToUse": "定价策略、产品定价、价格优化、收入模型",
      "systemPrompt": "帮助制定和优化产品/服务的定价策略，分析不同定价方法的优势和适用场景。",
      "inputFormat": "**必需信息**：\n```\n产品/服务：[名称]\n目标市场：[市场定义]\n业务模式：[一次性买断/订阅/Usage-based等]\n当前定价（如有）：[价格信息]\n```\n\n**可选补充**：\n- 成本结构\n- 竞品定价\n- 用户画像\n- 业务目标（市场份额/利润/增长）\n- 销售渠道",
      "path": "business\\pricing-strategy"
    },
    {
      "id": "project-plan",
      "name": "Project Plan",
      "category": "商业Business",
      "categoryKey": "business",
      "icon": "📄",
      "description": "项目计划制定技能。帮助制定项目计划，包含里程碑、资源分配、风险管理和进度安排。",
      "whenToUse": "项目计划、里程碑设定、资源规划、进度管理",
      "systemPrompt": "帮助制定完整的项目计划，包括时间线、里程碑、资源分配和风险管理。",
      "inputFormat": "**必需信息**：\n```\n项目名称：[名称]\n项目周期：[开始日期 - 结束日期]\n项目目标：[描述]\n项目负责人：[姓名]\n```\n\n**可选补充**：\n- 项目背景和动机\n- 团队成员列表\n- 预算限制\n- 依赖关系\n- 特殊约束",
      "path": "business\\project-plan"
    },
    {
      "id": "retention-analysis",
      "name": "Retention Analysis",
      "category": "商业Business",
      "categoryKey": "business",
      "icon": "📄",
      "description": "用户留存分析技能。帮助分析用户留存数据，识别流失原因，制定留存提升策略。",
      "whenToUse": "留存分析、用户流失、留存提升、cohort分析",
      "systemPrompt": "通过数据分析用户留存情况，识别流失原因，制定留存提升策略。",
      "inputFormat": "**必需信息**：\n```\n产品类型：[App/网站/订阅服务/电商等]\n分析周期：[时间段]\n核心行为：[定义什么是\"留存\"的行为]\n用户量级：[日活/月活/总用户]\n```\n\n**可选补充**：\n- 已有留存数据\n- 竞品留存数据\n- 用户画像\n- 产品阶段",
      "path": "business\\retention-analysis"
    },
    {
      "id": "risk-assessment",
      "name": "Risk Assessment",
      "category": "商业Business",
      "categoryKey": "business",
      "icon": "📄",
      "description": "风险识别与分析技能。帮助识别项目或业务中的各类风险，评估影响程度，制定应对策略。",
      "whenToUse": "风险管理、项目风险评估、业务风险、风险预案",
      "systemPrompt": "系统性地识别和评估风险，包括技术风险、业务风险、合规风险等，并制定应对策略。",
      "inputFormat": "**必需信息**：\n```\n评估对象：[项目/业务/产品名称]\n评估范围：[涉及的领域]\n评估目的：[管理风险/决策参考/合规要求]\n```\n\n**可选补充**：\n- 相关文档（项目计划、PRD、商业计划书）\n- 已有风险信息\n- 历史风险数据\n- 特定风险领域需重点关注",
      "path": "business\\risk-assessment"
    },
    {
      "id": "user-research",
      "name": "User Research",
      "category": "商业Business",
      "categoryKey": "business",
      "icon": "📄",
      "description": "用户调研问卷设计技能。帮助设计用户调研问卷、用户访谈提纲，优化问题设计，提升调研质量。",
      "whenToUse": "用户调研、问卷设计、访谈提纲、需求分析",
      "systemPrompt": "帮助设计用户调研问卷和访谈提纲，优化问题设计，确保收集到高质量的用户洞察。",
      "inputFormat": "**必需信息**：\n```\n调研目的：[描述]\n目标用户：[用户画像描述]\n调研方法：[问卷/访谈/可用性测试/混合]\n样本量要求：[如：有效问卷≥300份]\n```\n\n**可选补充**：\n- 核心问题/假设清单\n- 竞品或行业参考\n- 预算和时间限制\n- 已有用户数据",
      "path": "business\\user-research"
    },
    {
      "id": "ab-test",
      "name": "Ab Test",
      "category": "数据Data",
      "categoryKey": "data",
      "icon": "📄",
      "description": "A/B测试实验设计技能。帮助设计A/B测试方案，计算样本量，确定统计显著性。",
      "whenToUse": "A/B测试、实验设计、转化率优化、数据实验",
      "systemPrompt": "帮助设计和分析A/B测试实验，优化产品决策。",
      "inputFormat": "",
      "path": "data\\ab-test"
    },
    {
      "id": "bi-report",
      "name": "Bi Report",
      "category": "数据Data",
      "categoryKey": "data",
      "icon": "📄",
      "description": "BI报表设计与配置技能。帮助设计BI报表和Dashboard，包括Tableau、PowerBI、Superset等工具。",
      "whenToUse": "BI报表、Dashboard、数据看板、BI配置",
      "systemPrompt": "帮助设计和配置BI报表和Dashboard，实现数据可视化。",
      "inputFormat": "",
      "path": "data\\bi-report"
    },
    {
      "id": "chart-designer",
      "name": "Chart Designer",
      "category": "数据Data",
      "categoryKey": "data",
      "icon": "📄",
      "description": "数据可视化图表设计技能。帮助选择合适的图表类型，设计清晰美观的数据可视化。",
      "whenToUse": "图表设计、数据可视化、报表设计、Dashboard",
      "systemPrompt": "帮助选择最合适的数据可视化方式，设计清晰、美观、有说服力的图表。",
      "inputFormat": "",
      "path": "data\\chart-designer"
    },
    {
      "id": "data-analyst",
      "name": "Data Analyst",
      "category": "数据Data",
      "categoryKey": "data",
      "icon": "📄",
      "description": "数据趋势分析与洞察技能。帮助分析数据趋势，识别模式，发现业务洞察，支持决策。",
      "whenToUse": "数据分析、趋势分析、业务洞察、数据报告",
      "systemPrompt": "帮助分析数据，发现趋势、模式和洞察，支持业务决策。",
      "inputFormat": "",
      "path": "data\\data-analyst"
    },
    {
      "id": "data-cleaner",
      "name": "Data Cleaner",
      "category": "数据Data",
      "categoryKey": "data",
      "icon": "📄",
      "description": "数据清洗与预处理技能。帮助处理数据中的缺失值、异常值、重复值，进行数据质量提升。",
      "whenToUse": "数据清洗、数据预处理、数据质量、ETL",
      "systemPrompt": "帮助清洗和预处理原始数据，处理缺失值、异常值、重复值等问题。",
      "inputFormat": "",
      "path": "data\\data-cleaner"
    },
    {
      "id": "data-dict",
      "name": "Data Dict",
      "category": "数据Data",
      "categoryKey": "data",
      "icon": "📄",
      "description": "数据字典生成技能。帮助生成数据字典文档，包括字段说明、数据血缘和元数据管理。",
      "whenToUse": "数据字典、元数据、数据治理、数据血缘",
      "systemPrompt": "帮助生成和维护数据字典，确保数据定义清晰、可追溯。",
      "inputFormat": "",
      "path": "data\\data-dict"
    },
    {
      "id": "data-migrate",
      "name": "Data Migrate",
      "category": "数据Data",
      "categoryKey": "data",
      "icon": "📄",
      "description": "数据迁移方案技能。帮助设计数据迁移方案，包括ETL、实时同步、回滚方案等。",
      "whenToUse": "数据迁移、ETL、数据同步、数据库迁移",
      "systemPrompt": "帮助设计和执行数据迁移方案，确保数据安全、完整。",
      "inputFormat": "",
      "path": "data\\data-migrate"
    },
    {
      "id": "data-viz-story",
      "name": "Data Viz Story",
      "category": "数据Data",
      "categoryKey": "data",
      "icon": "📄",
      "description": "数据故事叙述技能。帮助将数据转化为有说服力的故事，用于汇报和演讲。",
      "whenToUse": "数据汇报、数据演讲、数据故事、PPT数据",
      "systemPrompt": "帮助将数据分析结果转化为有说服力的故事，让数据汇报更具影响力。",
      "inputFormat": "",
      "path": "data\\data-viz-story"
    },
    {
      "id": "excel-formula",
      "name": "Excel Formula",
      "category": "数据Data",
      "categoryKey": "data",
      "icon": "📄",
      "description": "Excel公式编写技能。帮助编写复杂的Excel公式，包括统计、财务、查找、日期等函数。",
      "whenToUse": "Excel公式、函数编写、数据处理、表格计算",
      "systemPrompt": "帮助编写复杂的Excel公式，解决实际工作中的数据处理需求。",
      "inputFormat": "",
      "path": "data\\excel-formula"
    },
    {
      "id": "report-generator",
      "name": "Report Generator",
      "category": "数据Data",
      "categoryKey": "data",
      "icon": "📄",
      "description": "数据报告自动生成技能。帮助自动生成数据报表，包括Dashboard、周报、月报等。",
      "whenToUse": "数据报告、自动报表、Dashboard、周报月报",
      "systemPrompt": "帮助自动生成各类数据报告，提升数据汇报效率。",
      "inputFormat": "",
      "path": "data\\report-generator"
    },
    {
      "id": "sql-query",
      "name": "Sql Query",
      "category": "数据Data",
      "categoryKey": "data",
      "icon": "📄",
      "description": "SQL查询编写与优化技能。帮助编写复杂的SQL查询，进行数据提取和分析优化。",
      "whenToUse": "SQL查询、数据提取、数据库查询、SQL优化",
      "systemPrompt": "帮助编写复杂的SQL查询，支持数据分析、报表生成等需求。",
      "inputFormat": "",
      "path": "data\\sql-query"
    },
    {
      "id": "stats-model",
      "name": "Stats Model",
      "category": "数据Data",
      "categoryKey": "data",
      "icon": "📄",
      "description": "统计模型选择与应用技能。帮助选择合适的统计模型进行分析，包括回归、分类、聚类、时间序列等。",
      "whenToUse": "统计分析、统计建模、模型选择、数据建模",
      "systemPrompt": "帮助选择和应用合适的统计模型，解决实际问题。",
      "inputFormat": "",
      "path": "data\\stats-model"
    },
    {
      "id": "brand-design",
      "name": "Brand Design",
      "category": "设计Design",
      "categoryKey": "design",
      "icon": "📄",
      "description": "品牌视觉系统建议技能。帮助建立完整的品牌视觉系统，包括VI、字体、图像等规范。",
      "whenToUse": "品牌视觉、品牌规范、VI设计、视觉系统",
      "systemPrompt": "帮助建立完整的品牌视觉系统，提供设计规范和指导。包括Logo系统、色彩系统、字体系统、图像风格、图标系统、组件规范等，确保品牌视觉的一致性和可复用性。",
      "inputFormat": "",
      "path": "design\\brand-design"
    },
    {
      "id": "color-scheme",
      "name": "Color Scheme",
      "category": "设计Design",
      "categoryKey": "design",
      "icon": "📄",
      "description": "配色方案建议技能。提供专业的配色建议，包括主色、辅色、渐变等设计。",
      "whenToUse": "配色设计、颜色搭配、品牌色彩、UI配色",
      "systemPrompt": "提供专业的配色方案建议，帮助建立视觉统一的设计语言。包括色彩心理学应用、色盲友好设计、色彩系统构建等专业内容。",
      "inputFormat": "",
      "path": "design\\color-scheme"
    },
    {
      "id": "design-system",
      "name": "Design System",
      "category": "设计Design",
      "categoryKey": "design",
      "icon": "📄",
      "description": "设计系统规范建议技能。帮助建立设计系统，包括组件库、设计令牌、原子设计等。",
      "whenToUse": "设计系统、组件库、设计规范、原子设计",
      "systemPrompt": "帮助建立完整的设计系统，提供组件规范和设计原则。从设计令牌到原子设计，从组件规范到模式库，构建可扩展、可维护的数字化产品设计体系。",
      "inputFormat": "",
      "path": "design\\design-system"
    },
    {
      "id": "font-pairing",
      "name": "Font Pairing",
      "category": "设计Design",
      "categoryKey": "design",
      "icon": "📄",
      "description": "字体搭配建议技能。提供中英文字体搭配建议，建立视觉统一的设计语言。",
      "whenToUse": "字体设计、字体搭配、字体选择、版式设计",
      "systemPrompt": "帮助选择和搭配字体，建立统一的视觉语言。涵盖字体选择原则、中英文搭配、字体层级设计、字号规范等内容，确保字体的可读性和美观性。",
      "inputFormat": "",
      "path": "design\\font-pairing"
    },
    {
      "id": "icon-picker",
      "name": "Icon Picker",
      "category": "设计Design",
      "categoryKey": "design",
      "icon": "📄",
      "description": "图标选型建议技能。推荐适合的图标风格和资源。",
      "whenToUse": "图标选择、icon设计、图标资源、设计规范",
      "systemPrompt": "帮助选择适合产品风格的图标，提供图标库推荐、风格建议、尺寸规范和使用指导。确保图标的视觉一致性和功能可用性。",
      "inputFormat": "",
      "path": "design\\icon-picker"
    },
    {
      "id": "logo-ideation",
      "name": "Logo Ideation",
      "category": "设计Design",
      "categoryKey": "design",
      "icon": "📄",
      "description": "Logo设计概念头脑风暴技能。帮助梳理Logo设计方向，提供创意概念和元素建议。",
      "whenToUse": "Logo设计、品牌标识、创意头脑风暴、VI设计",
      "systemPrompt": "帮助进行Logo设计的头脑风暴，梳理品牌DNA，提炼设计方向，提供多个创意概念供选择。从品牌战略高度思考Logo设计，提供可执行的创意方向。",
      "inputFormat": "",
      "path": "design\\logo-ideation"
    },
    {
      "id": "poster-layout",
      "name": "Poster Layout",
      "category": "设计Design",
      "categoryKey": "design",
      "icon": "📄",
      "description": "宣传海报布局建议技能。提供海报设计建议，包括构图、层次、布局等。",
      "whenToUse": "海报设计、宣传物料、视觉布局、构图建议",
      "systemPrompt": "提供海报设计的布局和构图建议，提升视觉效果。涵盖构图原则、信息层级、色彩搭配、尺寸规范等内容，帮助创建有效的视觉传播物料。",
      "inputFormat": "",
      "path": "design\\poster-layout"
    },
    {
      "id": "slide-deck",
      "name": "Slide Deck",
      "category": "设计Design",
      "categoryKey": "design",
      "icon": "📄",
      "description": "演示文稿内容规划技能。帮助规划PPT/Keynote的结构和内容，提供演讲建议。",
      "whenToUse": "PPT制作、演示文稿、演讲准备、汇报结构",
      "systemPrompt": "帮助规划和制作演示文稿，提供结构设计、内容组织和演讲建议。从受众分析到信息架构，从视觉设计到演讲技巧，提供完整的演示文稿解决方案。",
      "inputFormat": "",
      "path": "design\\slide-deck"
    },
    {
      "id": "ui-feedback",
      "name": "Ui Feedback",
      "category": "设计Design",
      "categoryKey": "design",
      "icon": "📄",
      "description": "UI界面设计反馈技能。提供UI设计评审和改进建议，包括布局、配色、字体、交互等。",
      "whenToUse": "UI设计、设计评审、界面优化、交互设计",
      "systemPrompt": "对UI设计提供专业评审和改进建议，覆盖布局、配色、字体、交互等维度，帮助识别设计问题并提供可执行的优化方案。",
      "inputFormat": "",
      "path": "design\\ui-feedback"
    },
    {
      "id": "ux-review",
      "name": "Ux Review",
      "category": "设计Design",
      "categoryKey": "design",
      "icon": "📄",
      "description": "用户体验评估技能。评估产品用户体验，提供流程优化和交互改进建议。",
      "whenToUse": "用户体验、交互评估、可用性测试、用户研究",
      "systemPrompt": "评估产品用户体验，从可用性、可访问性、效率、容错性等维度分析用户流程，识别体验问题并提供可量化的改进建议。",
      "inputFormat": "",
      "path": "design\\ux-review"
    },
    {
      "id": "coding-tutor",
      "name": "Coding Tutor",
      "category": "教育Education",
      "categoryKey": "education",
      "icon": "📄",
      "description": "编程教学与代码调试技能。支持Python、Java、JavaScript等语言，提供编程教学、代码调试、算法解释和项目指导。",
      "whenToUse": "编程学习、代码调试、算法理解、项目开发",
      "systemPrompt": "为编程学习者提供代码教学、调试帮助和项目指导，培养编程思维和解决问题的能力。",
      "inputFormat": "```\n学习内容：[如\"递归\"、\"面向对象\"、\"排序算法\"]\n语言/框架：[如\"Python\"、\"JavaScript\"]\n当前水平：[可选，如\"入门\"、\"进阶\"]\n学习目标：[可选，如\"理解原理\"、\"能够实现\"]\n```",
      "path": "education\\coding-tutor"
    },
    {
      "id": "essay-review",
      "name": "Essay Review",
      "category": "教育Education",
      "categoryKey": "education",
      "icon": "📄",
      "description": "作文批改与润色技能。支持议论文、记叙文、说明文等各类作文，提供结构优化、语言润色和写作建议。",
      "whenToUse": "作文批改、写作指导、润色修改、文章优化",
      "systemPrompt": "帮助用户批改和优化作文，从立意、结构、语言、素材等多维度提供写作指导。",
      "inputFormat": "```\n作文内容：[完整的作文文本]\n文体类型：[如\"议论文\"、\"记叙文\"]\n年级/要求：[可选，如\"高三\"、\"高考水平\"]\n批改重点：[可选，如\"结构\"、\"语言\"、\"立意\"]\n```",
      "path": "education\\essay-review"
    },
    {
      "id": "exam-prep",
      "name": "Exam Prep",
      "category": "教育Education",
      "categoryKey": "education",
      "icon": "📄",
      "description": "考试备考策略与计划技能。为中考、高考、考研、托福、雅思等考试提供个性化备考方案、时间规划和应试技巧指导。",
      "whenToUse": "考试准备、备考计划、应试技巧、时间管理",
      "systemPrompt": "为用户提供考试备考的全面指导，包括计划制定、知识点梳理、模拟训练和应试技巧。",
      "inputFormat": "```\n考试类型：[具体考试名称]\n目标分数：[可选，如\"600分\"、\"7分\"]\n可用时间：[如\"100天\"、\"3个月\"]\n当前水平：[可选，如\"中等\"、\"已完成第一轮复习\"]\n薄弱科目：[可选，如\"数学\"、\"听力\"]\n```",
      "path": "education\\exam-prep"
    },
    {
      "id": "flashcard-generator",
      "name": "Flashcard Generator",
      "category": "教育Education",
      "categoryKey": "education",
      "icon": "📄",
      "description": "闪卡生成与记忆辅助技能。根据用户提供的知识点自动生成闪卡（问答对），支持间隔重复记忆法，帮助高效记忆。",
      "whenToUse": "知识点记忆、卡片制作、间隔重复、学习背诵",
      "systemPrompt": "将知识点转化为问答形式的闪卡，支持间隔重复复习计划，帮助用户高效记忆。",
      "inputFormat": "```\n知识点：[需要生成闪卡的内容]\n科目/主题：[如\"历史\"、\"数学\"、\"英语\"]\n数量要求：[可选，如\"10张\"、\"全部\"]\n格式要求：[可选，如\"问答对\"、\"只问不答\"]\n```",
      "path": "education\\flashcard-generator"
    },
    {
      "id": "homework-biology",
      "name": "Homework Biology",
      "category": "教育Education",
      "categoryKey": "education",
      "icon": "📄",
      "description": "中小学生物题目解答与讲解技能。当用户发送生物题目（细胞、遗传、生态、进化等）时自动触发。提供详细解答和知识点讲解。",
      "whenToUse": "生物题目求解、作业帮助、试题讲解、知识点答疑",
      "systemPrompt": "帮助用户解答中小学生物题目，提供详细的解答和知识点讲解。",
      "inputFormat": "```\n题目内容：[具体题目文本]\n年级/难度：[可选，如\"高一\"、\"高考难度\"]\n题型：[可选，如\"选择题\"、\"填空题\"、\"简答题\"]\n```",
      "path": "education\\homework-biology"
    },
    {
      "id": "homework-chemistry",
      "name": "Homework Chemistry",
      "category": "教育Education",
      "categoryKey": "education",
      "icon": "📄",
      "description": "中小学化学题目解答与讲解技能。当用户发送化学题目（反应方程式、计算题、物质性质等）时自动触发。提供详细解题步骤、反应原理和知识点讲解。",
      "whenToUse": "化学题目求解、作业帮助、试题讲解、知识点答疑",
      "systemPrompt": "帮助用户解答中小学化学题目，提供详细的解题步骤、反应原理和知识点讲解。",
      "inputFormat": "```\n题目内容：[具体题目文本]\n年级/难度：[可选，如\"初三\"、\"高考难度\"]\n已知条件：[可选，明确标注已知量]\n求解目标：[可选，明确要求求解的化学量]\n```",
      "path": "education\\homework-chemistry"
    },
    {
      "id": "homework-chinese",
      "name": "Homework Chinese",
      "category": "教育Education",
      "categoryKey": "education",
      "icon": "📄",
      "description": "语文题目解答技能。支持阅读理解、文言文翻译、作文指导。提供现代文阅读技巧、古文翻译和写作思路指导。",
      "whenToUse": "语文题目求解、阅读理解、文言文翻译、作文指导",
      "systemPrompt": "帮助用户解答语文题目，提供阅读理解技巧、文言文翻译和写作指导。",
      "inputFormat": "```\n题目内容：[具体题目文本或描述]\n年级/难度：[可选，如\"高一\"、\"高考难度\"]\n题型：[可选，如\"阅读理解\"、\"文言文翻译\"、\"作文\"]\n篇目信息：[可选，如文章标题、作者]\n```",
      "path": "education\\homework-chinese"
    },
    {
      "id": "homework-english",
      "name": "Homework English",
      "category": "教育Education",
      "categoryKey": "education",
      "icon": "📄",
      "description": "英语题目解答技能。支持阅读理解、完形填空、写作、翻译等各类题目。提供解题技巧讲解和英语能力提升建议。",
      "whenToUse": "英语题目求解、阅读理解、写作修改、翻译润色",
      "systemPrompt": "帮助用户解答各类英语题目，提供解题技巧和语言能力提升建议。",
      "inputFormat": "```\n题目内容：[具体题目文本或描述]\n年级/难度：[可选，如\"高二\"、\"高考难度\"]\n题型：[可选，如\"阅读理解\"、\"完形填空\"、\"写作\"]\n题目原文：[可选，如有原文材料]\n```",
      "path": "education\\homework-english"
    },
    {
      "id": "homework-geography",
      "name": "Homework Geography",
      "category": "教育Education",
      "categoryKey": "education",
      "icon": "📄",
      "description": "中小学地理题目解答技能。当用户发送地理题目（地图、气候、区位等）时自动触发。提供详细的分析和知识点讲解。",
      "whenToUse": "地理题目求解、地图判读、气候分析、区位选择",
      "systemPrompt": "帮助用户解答地理题目，提供地图判读、气候分析、区位选择等问题的详细解答。",
      "inputFormat": "```\n题目内容：[具体题目文本或描述]\n年级/难度：[可选，如\"高一\"、\"高考难度\"]\n题型：[可选，如\"选择题\"、\"简答题\"、\"读图题\"]\n图文信息：[可选，描述地图或图表的关键信息]\n```",
      "path": "education\\homework-geography"
    },
    {
      "id": "homework-history",
      "name": "Homework History",
      "category": "教育Education",
      "categoryKey": "education",
      "icon": "📄",
      "description": "中小学历史题目分析技能。当用户发送历史题目（历史事件、人物、时间线等）时自动触发。提供详细分析和知识点讲解。",
      "whenToUse": "历史题目求解、作业帮助、试题分析、知识点答疑",
      "systemPrompt": "帮助用户分析历史题目，提供详细的历史背景分析、事件关联和知识点讲解。",
      "inputFormat": "```\n题目内容：[具体题目文本]\n年级/难度：[可选，如\"初三\"、\"高考难度\"]\n题型：[可选，如\"选择题\"、\"简答题\"、\"论述题\"]\n```",
      "path": "education\\homework-history"
    },
    {
      "id": "homework-math",
      "name": "Homework Math",
      "category": "教育Education",
      "categoryKey": "education",
      "icon": "📄",
      "description": "中小学数学题目解答与讲解技能。当用户发送数学题目（方程、几何、概率、应用题等）时自动触发。提供详细解题步骤、思路分析和知识点讲解。",
      "whenToUse": "数学题目求解、作业帮助、试题讲解、知识点答疑",
      "systemPrompt": "帮助用户解答中小学数学题目，提供详细的解题步骤和思路讲解。",
      "inputFormat": "```\n题目内容：[具体题目文本]\n年级/难度：[可选，如\"初三\"、\"高考难度\"]\n特殊要求：[可选，如\"用配方法\"、\"只给思路\"]\n```",
      "path": "education\\homework-math"
    },
    {
      "id": "homework-physics",
      "name": "Homework Physics",
      "category": "教育Education",
      "categoryKey": "education",
      "icon": "📄",
      "description": "中小学物理题目解答与讲解技能。当用户发送物理题目（力学、电学、光学、热学等）时自动触发。提供详细解题步骤、公式运用和概念讲解。",
      "whenToUse": "物理题目求解、作业帮助、试题讲解、知识点答疑",
      "systemPrompt": "帮助用户解答中小学物理题目，提供详细的解题步骤、公式运用和概念讲解。",
      "inputFormat": "```\n题目内容：[具体题目文本]\n年级/难度：[可选，如\"高一\"、\"高考难度\"]\n已知条件：[可选，明确标注已知量]\n求解目标：[可选，明确要求求解的物理量]\n```",
      "path": "education\\homework-physics"
    },
    {
      "id": "homework-politics",
      "name": "Homework Politics",
      "category": "教育Education",
      "categoryKey": "education",
      "icon": "📄",
      "description": "政治/道德与法治题目解答技能。提供经济现象分析、政治制度理解、哲学思维培养和时事热点的题目解答。",
      "whenToUse": "政治题目求解、时事分析、道德判断、法治意识",
      "systemPrompt": "帮助用户解答思想政治、道德与法治题目，提供时事分析、制度理解和价值判断的指导。",
      "inputFormat": "```\n题目内容：[具体题目文本]\n年级/难度：[可选，如\"高三\"、\"高考难度\"]\n题型：[可选，如\"选择题\"、\"简答题\"、\"论述题\"]\n考察模块：[可选，如\"经济\"、\"政治\"、\"哲学\"]\n```",
      "path": "education\\homework-politics"
    },
    {
      "id": "knowledge-explainer",
      "name": "Knowledge Explainer",
      "category": "教育Education",
      "categoryKey": "education",
      "icon": "📄",
      "description": "复杂概念通俗讲解技能。将专业术语和复杂概念用通俗易懂的语言解释，配合实例和类比帮助理解。",
      "whenToUse": "概念理解、知识讲解、原理分析、术语解释",
      "systemPrompt": "用通俗易懂的语言解释复杂的专业概念，配合生活实例和类比，帮助用户真正理解而非死记硬背。",
      "inputFormat": "```\n概念名称：[需要解释的概念]\n当前理解程度：[可选，如\"完全不了解\"、\"有一点了解\"]\n重点关注：[可选，如\"实际应用\"、\"推导过程\"]\n```",
      "path": "education\\knowledge-explainer"
    },
    {
      "id": "language-tutor",
      "name": "Language Tutor",
      "category": "教育Education",
      "categoryKey": "education",
      "icon": "📄",
      "description": "外语学习辅导技能。支持英语、日语、法语等外语学习，提供发音纠正、口语练习、写作指导、听力训练等多维度的学习支持。",
      "whenToUse": "外语学习、口语练习、写作纠正、发音指导",
      "systemPrompt": "为外语学习者提供全方位的学习辅导，包括发音、口语、写作、听力等技能训练。",
      "inputFormat": "```\n学习语言：[如\"英语\"、\"日语\"]\n学习目标：[如\"口语提升\"、\"写作纠正\"]\n当前水平：[如\"CET-4\"、\"N3\"]\n具体需求：[可选，如\"发音纠正\"、\"作文批改\"]\n```",
      "path": "education\\language-tutor"
    },
    {
      "id": "note-organizer",
      "name": "Note Organizer",
      "category": "教育Education",
      "categoryKey": "education",
      "icon": "📄",
      "description": "笔记整理与知识梳理技能。支持康奈尔笔记法、思维导图、大纲笔记等多种格式，帮助用户整理学习笔记、构建知识体系。",
      "whenToUse": "笔记整理、知识梳理、复习总结、学习归纳",
      "systemPrompt": "帮助用户整理和优化学习笔记，支持多种笔记方法，构建清晰的知识体系。",
      "inputFormat": "```\n原始内容：[笔记内容、教材要点或学习材料]\n当前状态：[可选，如\"零散笔记\"、\"教材划线内容\"]\n笔记类型：[可选，如\"康奈尔\"、\"思维导图\"、\"大纲\"]\n整理目的：[可选，如\"复习迎考\"、\"构建体系\"]\n```",
      "path": "education\\note-organizer"
    },
    {
      "id": "science-lab",
      "name": "Science Lab",
      "category": "教育Education",
      "categoryKey": "education",
      "icon": "📄",
      "description": "实验报告撰写与实验指导技能。支持物理、化学、生物实验，提供实验原理分析、数据处理和报告撰写指导。",
      "whenToUse": "实验报告、实验原理、数据处理、实验设计",
      "systemPrompt": "帮助用户完成实验报告，解释实验原理，指导数据处理和分析。",
      "inputFormat": "```\n实验名称：[实验的具体名称]\n实验类型：[如\"物理\"、\"化学\"、\"生物\"]\n实验阶段：[可选，如\"设计阶段\"、\"数据处理\"、\"报告撰写\"]\n具体需求：[可选，如\"帮我写报告\"、\"帮我处理数据\"]\n原始数据：[如果有的话]\n```",
      "path": "education\\science-lab"
    },
    {
      "id": "study-plan",
      "name": "Study Plan",
      "category": "教育Education",
      "categoryKey": "education",
      "icon": "📄",
      "description": "个性化学习计划制定技能。根据用户的目标、时间和现有水平，制定科学的学习计划，包含复习节奏、时间管理和阶段性目标。",
      "whenToUse": "学习计划制定、时间管理、复习节奏、目标设定",
      "systemPrompt": "帮助用户制定科学合理的个性化学习计划，包括学科规划、时间管理和进度追踪。",
      "inputFormat": "```\n学习目标：[具体目标，如\"Python编程\"、\"英语口语\"]\n总时长：[如\"3个月\"、\"一学期\"]\n每周可用时间：[如\"10小时\"、\"每天2小时\"]\n当前水平：[如\"零基础\"、\"中级\"]\n学习风格：[可选，如\"视觉型\"、\"听觉型\"、\"动手型\"]\n```",
      "path": "education\\study-plan"
    },
    {
      "id": "book-summary",
      "name": "Book Summary",
      "category": "生活Life",
      "categoryKey": "life",
      "icon": "📄",
      "description": "书籍总结与笔记技能。帮助提炼书籍的核心观点，生成精华笔记和行动指南。",
      "whenToUse": "读书笔记、书籍总结、精华提炼、阅读推荐",
      "systemPrompt": "帮助总结书籍的核心内容，提炼精华观点，提供行动指南。",
      "inputFormat": "",
      "path": "life\\book-summary"
    },
    {
      "id": "finance-advisor",
      "name": "Finance Advisor",
      "category": "生活Life",
      "categoryKey": "life",
      "icon": "📄",
      "description": "个人理财建议技能。帮助规划预算、储蓄、投资和税务，提供个人财务建议。",
      "whenToUse": "理财规划、预算管理、投资建议、储蓄",
      "systemPrompt": "提供个人理财建议，包括预算规划、储蓄策略、投资配置等。",
      "inputFormat": "",
      "path": "life\\finance-advisor"
    },
    {
      "id": "fitness-plan",
      "name": "Fitness Plan",
      "category": "生活Life",
      "categoryKey": "life",
      "icon": "📄",
      "description": "健身计划制定技能。帮助制定个性化的健身计划，包括增肌、减脂、力量训练等。",
      "whenToUse": "健身计划、增肌减脂、运动训练、体态改善",
      "systemPrompt": "帮助制定个性化的健身计划，实现增肌、减脂或提升体能目标。",
      "inputFormat": "",
      "path": "life\\fitness-plan"
    },
    {
      "id": "gift-advisor",
      "name": "Gift Advisor",
      "category": "生活Life",
      "categoryKey": "life",
      "icon": "📄",
      "description": "礼品推荐建议技能。根据场景、对象、预算推荐合适的礼品。",
      "whenToUse": "礼品推荐、送礼建议、礼物选择、节日礼物",
      "systemPrompt": "帮助用户选择合适的礼品，根据不同场景、对象和预算。",
      "inputFormat": "",
      "path": "life\\gift-advisor"
    },
    {
      "id": "health-advisor",
      "name": "Health Advisor",
      "category": "生活Life",
      "categoryKey": "life",
      "icon": "📄",
      "description": "健康生活建议技能。提供饮食、运动、作息等方面的健康建议。",
      "whenToUse": "健康咨询、饮食建议、运动计划、养生",
      "systemPrompt": "提供科学的健康生活建议，包括饮食、运动、作息等方面。",
      "inputFormat": "",
      "path": "life\\health-advisor"
    },
    {
      "id": "home-reno",
      "name": "Home Reno",
      "category": "生活Life",
      "categoryKey": "life",
      "icon": "📄",
      "description": "家居装修建议技能。提供装修风格、空间规划、收纳设计等建议。",
      "whenToUse": "装修建议、家居设计、空间规划、软装搭配",
      "systemPrompt": "提供家居装修和设计的建议，包括风格选择、空间规划、软装搭配等。",
      "inputFormat": "",
      "path": "life\\home-reno"
    },
    {
      "id": "movie-recommender",
      "name": "Movie Recommender",
      "category": "生活Life",
      "categoryKey": "life",
      "icon": "📄",
      "description": "电影推荐系统技能。根据口味推荐电影，提供影评和观看指南。",
      "whenToUse": "电影推荐、观影指南、影评、口碑电影",
      "systemPrompt": "根据用户喜好推荐电影，提供观影指南和简要影评。",
      "inputFormat": "",
      "path": "life\\movie-recommender"
    },
    {
      "id": "music-playlist",
      "name": "Music Playlist",
      "category": "生活Life",
      "categoryKey": "life",
      "icon": "📄",
      "description": "音乐播放列表生成技能。根据场景、心情、年代等推荐音乐，生成个性化播放列表。",
      "whenToUse": "音乐推荐、歌单、播放列表、场景音乐",
      "systemPrompt": "根据用户需求生成音乐播放列表，适合不同场景和心情。",
      "inputFormat": "",
      "path": "life\\music-playlist"
    },
    {
      "id": "pet-care",
      "name": "Pet Care",
      "category": "生活Life",
      "categoryKey": "life",
      "icon": "📄",
      "description": "宠物养护建议技能。提供宠物喂养、训练、健康护理等方面的建议。",
      "whenToUse": "宠物喂养、宠物训练、宠物健康、宠物养护",
      "systemPrompt": "提供宠物养护建议，包括喂养、训练、健康护理等方面的指导。",
      "inputFormat": "",
      "path": "life\\pet-care"
    },
    {
      "id": "photo-tips",
      "name": "Photo Tips",
      "category": "生活Life",
      "categoryKey": "life",
      "icon": "📄",
      "description": "摄影技巧指导技能。提供构图、用光、参数设置等摄影指导。",
      "whenToUse": "摄影技巧、拍照指导、构图建议、相机设置",
      "systemPrompt": "提供摄影技巧指导，包括构图、用光、参数设置等。",
      "inputFormat": "",
      "path": "life\\photo-tips"
    },
    {
      "id": "recipe-recommender",
      "name": "Recipe Recommender",
      "category": "生活Life",
      "categoryKey": "life",
      "icon": "📄",
      "description": "食谱推荐技能。根据季节、口味、食材推荐食谱，提供营养搭配和烹饪指导。",
      "whenToUse": "食谱推荐、做饭灵感、营养搭配、烹饪教程",
      "systemPrompt": "根据用户需求推荐合适的食谱，提供烹饪方法。",
      "inputFormat": "",
      "path": "life\\recipe-recommender"
    },
    {
      "id": "schedule-planner",
      "name": "Schedule Planner",
      "category": "生活Life",
      "categoryKey": "life",
      "icon": "📄",
      "description": "日程管理与时间规划技能。帮助制定日/周/月计划，优化时间管理，提升效率。",
      "whenToUse": "日程规划、时间管理、效率提升、每日计划",
      "systemPrompt": "帮助用户规划日程，优化时间分配，提升工作和生活效率。",
      "inputFormat": "",
      "path": "life\\schedule-planner"
    },
    {
      "id": "shopping-advisor",
      "name": "Shopping Advisor",
      "category": "生活Life",
      "categoryKey": "life",
      "icon": "📄",
      "description": "产品推荐与比较技能。帮助推荐合适的产品，提供选购指南和避坑建议。",
      "whenToUse": "产品推荐、选购指南、购物比较、避坑",
      "systemPrompt": "帮助用户选择合适的产品，提供对比分析和选购建议。",
      "inputFormat": "",
      "path": "life\\shopping-advisor"
    },
    {
      "id": "travel-planner",
      "name": "Travel Planner",
      "category": "生活Life",
      "categoryKey": "life",
      "icon": "📄",
      "description": "旅行行程规划技能。帮助制定旅行计划，包括路线、住宿、预算、攻略等。",
      "whenToUse": "旅行规划、行程安排、自驾游、出国游",
      "systemPrompt": "帮助用户规划旅行，提供路线规划、住宿推荐、预算控制等。",
      "inputFormat": "",
      "path": "life\\travel-planner"
    },
    {
      "id": "career-coach",
      "name": "Career Coach",
      "category": "职业Professional",
      "categoryKey": "professional",
      "icon": "📄",
      "description": "职业发展规划建议技能。帮助分析职业问题，提供职业路径、转型建议和技能提升指导。",
      "whenToUse": "职业规划、职业转型、职业发展、工作选择",
      "systemPrompt": "帮助用户进行职业规划和发展分析，提供职业路径建议、技能提升指导和转型策略。",
      "inputFormat": "",
      "path": "professional\\career-coach"
    },
    {
      "id": "interview-prep",
      "name": "Interview Prep",
      "category": "职业Professional",
      "categoryKey": "professional",
      "icon": "📄",
      "description": "面试准备与预测技能。帮助准备面试，包括常见问题、面试技巧、模拟面试等。",
      "whenToUse": "面试准备、求职技巧、面试模拟、题库预测",
      "systemPrompt": "帮助用户全面准备面试，提供常见问题分析、答题技巧指导、模拟面试练习和公司研究框架。",
      "inputFormat": "",
      "path": "professional\\interview-prep"
    },
    {
      "id": "investment-analyst",
      "name": "Investment Analyst",
      "category": "职业Professional",
      "categoryKey": "professional",
      "icon": "📄",
      "description": "投资标的分析技能。帮助分析投资标的，提供投资逻辑、风险评估和配置建议。",
      "whenToUse": "投资分析、股票分析、基金选择、资产配置",
      "systemPrompt": "帮助用户理解投资分析框架，提供投资逻辑、风险评估和配置建议的基础知识教育。",
      "inputFormat": "",
      "path": "professional\\investment-analyst"
    },
    {
      "id": "legal-advisor",
      "name": "Legal Advisor",
      "category": "职业Professional",
      "categoryKey": "professional",
      "icon": "📄",
      "description": "法律风险提示技能。提供基础法律风险识别和提示，包括合同、劳动法、知识产权等。",
      "whenToUse": "法律咨询、合同风险、劳动法、知识产权",
      "systemPrompt": "提供基础法律风险识别和提示，帮助用户了解常见的法律问题及应对策略。",
      "inputFormat": "",
      "path": "professional\\legal-advisor"
    },
    {
      "id": "legal-doc",
      "name": "Legal Doc",
      "category": "职业Professional",
      "categoryKey": "professional",
      "icon": "📄",
      "description": "法律文书撰写技能。帮助撰写基础法律文书，包括合同、协议、律师函等。",
      "whenToUse": "法律文书、合同撰写、协议起草、律师函",
      "systemPrompt": "帮助用户撰写和理解基础法律文书，提供合同模板、协议起草指南和文书结构参考。",
      "inputFormat": "",
      "path": "professional\\legal-doc"
    },
    {
      "id": "mediator",
      "name": "Mediator",
      "category": "职业Professional",
      "categoryKey": "professional",
      "icon": "📄",
      "description": "冲突调解与协调技能。帮助调解人际冲突和矛盾，提供沟通技巧和解决方案。",
      "whenToUse": "冲突调解、人际矛盾、沟通协调、关系修复",
      "systemPrompt": "帮助用户分析人际冲突的根源，提供有效的沟通策略和解决方案，促进冲突的和平解决和关系的修复。",
      "inputFormat": "",
      "path": "professional\\mediator"
    },
    {
      "id": "therapy-chat",
      "name": "Therapy Chat",
      "category": "职业Professional",
      "categoryKey": "professional",
      "icon": "📄",
      "description": "情绪疏导与心理支持技能。提供情绪疏导、压力管理、coping策略等心理支持。",
      "whenToUse": "情绪疏导、压力管理、心理咨询、心理支持",
      "systemPrompt": "提供情绪疏导和心理支持对话，帮助用户缓解压力和负面情绪，提供 coping 策略和资源推荐。",
      "inputFormat": "",
      "path": "professional\\therapy-chat"
    },
    {
      "id": "blog-writer",
      "name": "Blog Writer",
      "category": "写作Writing",
      "categoryKey": "writing",
      "icon": "📄",
      "description": "博客文章创作技能。帮助创作各类博客文章，包括教程、观点文章、行业分析等，提供SEO友好的内容结构。",
      "whenToUse": "博客文章、技术教程、观点文章、行业分析",
      "systemPrompt": "创作各类博客文章，包括教程类、观点类、行业分析类，提供吸引读者的开头和SEO优化建议。",
      "inputFormat": "```\n【文章主题】XXX\n【文章类型】教程/观点/行业分析/产品评测/经验分享\n【目标读者】XXX（如：新手程序员、创业者、宝妈）\n【核心要点】1. XXX 2. XXX 3. XXX\n【字数要求】XXX（如：1500字左右）\n【SEO关键词】（可选）XXX\n【特殊要求】XXX（如：需要代码示例、需要配图建议）\n```",
      "path": "writing\\blog-writer"
    },
    {
      "id": "brand-story",
      "name": "Brand Story",
      "category": "写作Writing",
      "categoryKey": "writing",
      "icon": "📄",
      "description": "品牌叙事构建技能。帮助构建品牌故事，包括品牌起源、创始人故事、品牌价值观等，塑造有感染力的品牌形象。",
      "whenToUse": "品牌故事、创始人故事、品牌文化、价值观传播",
      "systemPrompt": "帮助品牌构建有感染力的叙事，包括品牌起源故事、创始人故事、品牌价值观等。",
      "inputFormat": "```\n【品牌名称】XXX\n【品牌类型】产品品牌/服务品牌/企业品牌\n【核心信息】\n- 创始时间/地点：XXX\n- 创始人背景：XXX\n- 创立契机/故事：XXX\n- 核心产品/服务：XXX\n- 品牌价值观：XXX\n【目标受众】XXX（如：追求品质的年轻消费者、企业客户）\n【故事用途】官网/宣传册/融资/招聘\n【篇幅要求】短版100字/中版300字/长版800字（可选）\n```",
      "path": "writing\\brand-story"
    },
    {
      "id": "copywriter",
      "name": "Copywriter",
      "category": "写作Writing",
      "categoryKey": "writing",
      "icon": "📄",
      "description": "营销文案创作技能。帮助创作广告语、产品文案、促销文案、销售页等营销内容，提升转化率。",
      "whenToUse": "广告文案、产品介绍、促销海报、销售页文案",
      "systemPrompt": "创作各类营销文案，包括广告语、产品文案、促销海报、销售页等，帮助提升营销效果。",
      "inputFormat": "```\n【产品/服务名称】XXX\n【产品/服务描述】XXX\n【目标受众】XXX（如：年轻女性、职场白领、企业采购）\n【核心卖点】1. XXX 2. XXX 3. XXX\n【文案类型】广告语/产品文案/促销文案/销售页/详情页\n【风格要求】年轻/专业/温情/幽默/高端/接地气（可选）\n【使用场景】XXX（如：朋友圈、电商详情页、电梯广告）\n```",
      "path": "writing\\copywriter"
    },
    {
      "id": "creative-writing",
      "name": "Creative Writing",
      "category": "写作Writing",
      "categoryKey": "writing",
      "icon": "📄",
      "description": "创意写作技能。帮助创作故事、诗歌、剧本、小说等文学作品，提供情节设计、人物塑造和文风指导。",
      "whenToUse": "故事创作、小说写作、诗歌创作、剧本编写",
      "systemPrompt": "帮助用户进行各类创意写作，包括故事创作、小说、诗歌、剧本等。",
      "inputFormat": "```\n【作品类型】短篇小说/微小说/诗歌/剧本/故事大纲/人物设定\n【主题/想法】XXX\n【风格】现实主义/魔幻现实/科幻/悬疑/温情/幽默\n【篇幅】XXX字/XXX分钟\n【目标读者】（可选）XXX\n【特殊要求】（可选）是否需要特定元素\n```",
      "path": "writing\\creative-writing"
    },
    {
      "id": "email-writer",
      "name": "Email Writer",
      "category": "写作Writing",
      "categoryKey": "writing",
      "icon": "📄",
      "description": "商务邮件撰写技能。帮助撰写各类商务邮件，包括开发信、跟进邮件、邀请函、道歉信等，提升专业沟通效果。",
      "whenToUse": "商务邮件、英文邮件、工作邮件、正式沟通",
      "systemPrompt": "创作各类商务邮件，包括开发信、跟进邮件、邀请函、道歉信等，确保邮件专业、有礼、有效。",
      "inputFormat": "```\n【邮件类型】开发信/跟进信/邀请函/道歉信/感谢信/报价信/会议邮件\n【收件人】姓名 + 公司/职位（如：王总，某大型企业采购总监）\n【发件人】姓名 + 公司 + 职位\n【邮件主题】（可选）XXX\n【核心信息】\n- 邮件背景：XXX\n- 主要诉求：XXX\n- 期望结果：XXX\n【附件】（可选）是否需要附带文件\n【邮件语】正式/友好/紧迫/诚恳（可选，默认正式）\n【语言】中文/英文\n```",
      "path": "writing\\email-writer"
    },
    {
      "id": "grammar-check",
      "name": "Grammar Check",
      "category": "写作Writing",
      "categoryKey": "writing",
      "icon": "📄",
      "description": "英文语法纠错技能。帮助检查和纠正英文写作中的语法错误，提供错误分析和正确表达。",
      "whenToUse": "英文纠错、语法检查、写作修改、语言学习",
      "systemPrompt": "帮助检查英文文本的语法、拼写、用词等错误，并提供错误分析和正确表达。",
      "inputFormat": "```\n【文本类型】邮件/文书/作业/聊天/其他\n【语法难度】基础/中级/高级\n【纠错重点】（可选）全部纠错/仅标点/仅用词\n【原文】\n...\n```",
      "path": "writing\\grammar-check"
    },
    {
      "id": "localization",
      "name": "Localization",
      "category": "写作Writing",
      "categoryKey": "writing",
      "icon": "📄",
      "description": "内容本地化翻译技能。将内容适配到目标语言和文化，不仅翻译文字，更考虑文化适配、本地习惯和法规要求。",
      "whenToUse": "本地化翻译、文化适配、海外市场、内容国际化",
      "systemPrompt": "帮助内容进行本地化适配，包括文化调整、用语本地化、法规合规等，让内容在目标市场更接地气。",
      "inputFormat": "```\n【内容类型】App界面/营销文案/产品说明/网站内容\n【源语言】中文/英文\n【源内容】XXX\n【目标市场】XXX（如：美国、日本、东南亚）\n【目标语言】（如：英语、日语）\n【文化背景】（可选）已知的文化特点\n【使用场景】XXX\n```",
      "path": "writing\\localization"
    },
    {
      "id": "press-release",
      "name": "Press Release",
      "category": "写作Writing",
      "categoryKey": "writing",
      "icon": "📄",
      "description": "新闻稿与公关稿撰写技能。帮助撰写产品发布、融资公布、危机公关等活动所需的新闻稿。",
      "whenToUse": "新闻稿、公关稿、产品发布、企业公告",
      "systemPrompt": "创作专业的新闻稿和公关稿，包括产品发布、融资公布、活动宣传、危机公关等。",
      "inputFormat": "```\n【新闻类型】产品发布/融资公告/活动报道/危机声明/人物专访\n【核心事件】XXX\n【关键信息】\n- 时间：XXX\n- 地点：XXX\n- 人物：XXX\n- 原因/背景：XXX\n- 结果/影响：XXX\n【数据支撑】（可选）XXX\n【公司/人物背景】（可选）XXX\n【发布渠道】XXX（如：财经媒体、行业媒体、大众媒体）\n```",
      "path": "writing\\press-release"
    },
    {
      "id": "product-desc",
      "name": "Product Desc",
      "category": "写作Writing",
      "categoryKey": "writing",
      "icon": "📄",
      "description": "电商产品描述技能。帮助撰写淘宝、京东、亚马逊等平台的商品详情页文案，提升转化率。",
      "whenToUse": "电商文案、产品详情页、淘宝详情、亚马逊描述",
      "systemPrompt": "创作电商平台的商品详情页文案，包括标题、主图文案、详情描述、买家秀文案等。",
      "inputFormat": "```\n【产品名称】XXX\n【目标平台】淘宝/京东/亚马逊/拼多多/小红书\n【产品类别】XXX（如：数码、美妆、家居、服饰）\n【核心卖点】1. XXX 2. XXX 3. XXX\n【价格/规格】（可选）XXX\n【目标用户】XXX（如：年轻女性、商务人士）\n【竞品信息】（可选）XXX\n```",
      "path": "writing\\product-desc"
    },
    {
      "id": "report-writer",
      "name": "Report Writer",
      "category": "写作Writing",
      "categoryKey": "writing",
      "icon": "📄",
      "description": "分析报告撰写技能。帮助撰写年度报告、调研报告、可行性报告等，提供专业的报告结构和数据分析。",
      "whenToUse": "分析报告、调研报告、年度报告、可行性研究",
      "systemPrompt": "帮助撰写各类分析报告，包括年度报告、调研报告、可行性研究报告等。",
      "inputFormat": "```\n【报告类型】经营分析/市场调研/可行性报告/行业报告/复盘报告\n【报告周期】（可选）2024年上半年/2024全年\n【目标读者】XXX（如：董事会、管理层、项目组）\n【核心数据】XXX（如：营收、用户数、转化率）\n【背景信息】XXX\n【报告目的】XXX\n```",
      "path": "writing\\report-writer"
    },
    {
      "id": "resume-optimize",
      "name": "Resume Optimize",
      "category": "写作Writing",
      "categoryKey": "writing",
      "icon": "📄",
      "description": "简历诊断与优化技能。帮助分析简历问题，提供排版、措辞、关键词等方面的优化建议，提升面试机会。",
      "whenToUse": "简历优化、求职指导、简历诊断、面试机会",
      "systemPrompt": "帮助用户诊断和优化简历，包括内容结构、语言表达、关键词优化、排版格式等。",
      "inputFormat": "**场景A - 已有简历：**\n```\n【简历内容】粘贴完整简历内容\n【目标岗位】XXX（如：产品经理）\n【简历语言】中文/英文\n【特殊要求】（可选）XXX\n```\n\n**场景B - 目标岗位分析：**\n```\n【目标岗位】XXX\n【目标公司类型】（可选）大厂/外企/创业公司\n【简历语言】中文/英文\n【请求】帮我分析这个岗位看重什么，我应该如何准备简历\n```",
      "path": "writing\\resume-optimize"
    },
    {
      "id": "seo-optimizer",
      "name": "Seo Optimizer",
      "category": "写作Writing",
      "categoryKey": "writing",
      "icon": "📄",
      "description": "SEO内容优化技能。帮助优化网页内容、博客文章的结构和关键词，提升搜索引擎排名和有机流量。",
      "whenToUse": "SEO优化、关键词布局、内容结构调整、网站排名",
      "systemPrompt": "帮助优化网页和文章内容，提升搜索引擎排名。包括关键词研究、标题优化、内容结构优化、内链策略等。",
      "inputFormat": "**场景A - 已有内容优化：**\n```\n【原始内容】粘贴文章/页面内容\n【目标关键词】XXX（如：空气炸锅选购指南）\n【竞争对手】（可选）参考页面URL\n【特殊要求】XXX\n```\n\n**场景B - 新内容SEO规划：**\n```\n【主题】XXX\n【目标关键词】主关键词 + 2-3个长尾关键词\n【文章长度】建议字数\n【竞争分析】（可选）是否需要竞品分析\n```",
      "path": "writing\\seo-optimizer"
    },
    {
      "id": "social-post",
      "name": "Social Post",
      "category": "写作Writing",
      "categoryKey": "writing",
      "icon": "📄",
      "description": "社交媒体内容创作技能。支持微博、小红书、抖音、知乎等平台，提供符合各平台调性的内容创作。",
      "whenToUse": "小红书、微博、知乎、抖音内容创作、社交媒体运营",
      "systemPrompt": "为不同社交媒体平台创作内容，包括微博、小红书、知乎、抖音等，确保内容符合平台调性和用户喜好。",
      "inputFormat": "```\n【目标平台】小红书/微博/知乎/抖音/公众号\n【内容主题】XXX\n【内容类型】种草/测评/教程/观点/日常分享\n【核心信息】1. XXX 2. XXX\n【风格偏好】（可选）接地气/高端/专业/搞笑\n【发布时间】（可选）最佳发布时间建议\n【互动目标】（可选）引导评论/收藏/转发\n```",
      "path": "writing\\social-post"
    },
    {
      "id": "summarizer",
      "name": "Summarizer",
      "category": "写作Writing",
      "categoryKey": "writing",
      "icon": "📄",
      "description": "长文摘要提取技能。帮助从长篇文章、报告、论文中提取关键信息，生成简洁准确的摘要。",
      "whenToUse": "文章摘要、报告总结、论文概要、要点提取",
      "systemPrompt": "从长文本中提取核心信息，生成结构化摘要，保留关键要点。",
      "inputFormat": "**场景A - 完整文本摘要：**\n```\n【文本内容】粘贴完整或大段文本\n【摘要类型】简略摘要/详细摘要/要点列表\n【字数要求】（可选）XXX字左右\n【侧重点】（可选）重点关注XXX方面\n```\n\n**场景B - 快速要点提取：**\n```\n【文本内容】粘贴文本\n【请求】帮我提取核心要点\n【格式】要点列表/时间线/对比表格\n```",
      "path": "writing\\summarizer"
    },
    {
      "id": "tech-writer",
      "name": "Tech Writer",
      "category": "写作Writing",
      "categoryKey": "writing",
      "icon": "📄",
      "description": "技术文档编写技能。帮助编写API文档、用户手册、开发指南、技术规范等专业的技术文档。",
      "whenToUse": "API文档、用户手册、开发指南、技术规范、技术博客",
      "systemPrompt": "创作各类技术文档，包括API文档、用户手册、开发指南等，确保技术信息清晰易懂。",
      "inputFormat": "```\n【文档类型】API文档/用户手册/开发指南/技术规范/Changelog\n【目标读者】XXX（如：前端开发工程师、运维人员、普通用户）\n【技术背景】\n- 接口/功能描述：XXX\n- 请求/响应格式：XXX\n- 错误码说明：XXX\n- 示例代码：XXX（可选）\n【特殊要求】XXX（如：需要Markdown格式、需要包含 UML 图）\n```",
      "path": "writing\\tech-writer"
    },
    {
      "id": "translator",
      "name": "Translator",
      "category": "写作Writing",
      "categoryKey": "writing",
      "icon": "📄",
      "description": "中英文互译润色技能。提供高质量的中译英、英译中翻译，以及现有译文的润色优化。",
      "whenToUse": "翻译、英文润色、中英互译、语言优化",
      "systemPrompt": "提供专业的中英文互译服务，以及现有译文的润色优化，确保语言地道流畅。",
      "inputFormat": "```\n【翻译类型】中译英/英译中/润色校对\n【原文语言】中文/英文\n【风格要求】正式/商务/技术/文学/日常\n【专业领域】（可选）通用/金融/法律/医学/IT/营销\n【语境说明】（可选）使用场景、目标读者\n【保密要求】（可选）是否需要保密处理\n```",
      "path": "writing\\translator"
    }
  ]
}